[
	{"State": "P", "Name": "RallyHOLiC", "No": "3", "Peroid": "Apr 4, 2021 - Jun 19, 2021", "Group": "Category RC1 / RC2", "File": "", "Updated": ""},	
	{"State": "P", "Name": "RallyHOLiC", "No": "2", "Peroid": "Jan 3, 2021 - Mar 27, 2021", "Group": "Category RC2", "File": "rbrcz_rallyholic_2_rc2.json", "Updated": "( Last updated: Mar 7, 2021 )"},
	{"State": "P", "Name": "RallyHOLiC", "No": "2", "Peroid": "Jan 3, 2021 - Mar 27, 2021", "Group": "Category RC4", "File": "rbrcz_rallyholic_2_rc4.json", "Updated": "( Last updated: Mar 7, 2021 )"},
	{"State": "E", "Name": "RallyHOLiC", "No": "1", "Peroid": "Oct 4, 2020 - Dec 26, 2020", "Group": "Category RC2", "File": "rbrcz_rallyholic_1_rc2.json", "Updated": "( Last updated: Dec 20, 2020 )"},
	{"State": "E", "Name": "RallyHOLiC", "No": "1", "Peroid": "Oct 4, 2020 - Dec 26, 2020", "Group": "Category RC4", "File": "rbrcz_rallyholic_1_rc4.json", "Updated": "( Last updated: Dec 20, 2020 )"}
]
